<collusion score='0.0' system='sciplag'>
    <document id='suspicious-document00935.txt' src='suspicious-document00935.txt' original='suspicious-document00935.txt' format='txt'>
        <feature id='c5242922-11cf-4569-82df-22db011e8b58' type='summary' start='5940' length='604' value='null'/>
    </document>
    <document id='source-document00859.txt' src='source-document00859.txt' original='source-document00859.txt' format='txt'>
        <feature id='7744ff67-37be-4903-a6ff-3d83f35d36ea' type='paragraph' start='1' length='4716' value='null'/>
    </document>
    <alignments>
        <match score='0.0' type='summary'>
            <ref document='suspicious-document00935.txt' feature='c5242922-11cf-4569-82df-22db011e8b58' />
            <ref document='source-document00859.txt' feature='7744ff67-37be-4903-a6ff-3d83f35d36ea' />
            <detail>
                <detail name='type'>summary</detail>
            </detail>
        </match>
    </alignments>
</collusion>