<collusion score='0.0' system='sciplag'>
    <document id='suspicious-document01369.txt' src='suspicious-document01369.txt' original='suspicious-document01369.txt' format='txt'>
        <feature id='2a9b6a4c-8283-46f7-930b-f242ea6b4d97' type='translation' start='18649' length='320' value='null'/>
    </document>
    <document id='source-document03109.txt' src='source-document03109.txt' original='source-document03109.txt' format='txt'>
        <feature id='5c1ee36e-2ccc-44ad-aab1-ae2f9d031ebe' type='paragraph' start='1931' length='334' value='null'/>
    </document>
    <alignments>
        <match score='0.0' type='translation'>
            <ref document='suspicious-document01369.txt' feature='2a9b6a4c-8283-46f7-930b-f242ea6b4d97' />
            <ref document='source-document03109.txt' feature='5c1ee36e-2ccc-44ad-aab1-ae2f9d031ebe' />
            <detail>
                <detail name='type'>translation</detail>
            </detail>
        </match>
    </alignments>
</collusion>