<collusion score='0.0' system='sciplag'>
    <document id='suspicious-document01698.txt' src='suspicious-document01698.txt' original='suspicious-document01698.txt' format='txt'>
        <feature id='6ac8e34e-3574-47d9-b6e1-3d06ec1ea380' type='copy_and_paste' start='18940' length='704' value='null'/>
    </document>
    <document id='source-document00581.txt' src='source-document00581.txt' original='source-document00581.txt' format='txt'>
        <feature id='26d6e8cd-e007-467c-ad0f-d15de7e6c231' type='paragraph' start='1' length='704' value='null'/>
    </document>
    <alignments>
        <match score='0.0' type='copy_and_paste'>
            <ref document='suspicious-document01698.txt' feature='6ac8e34e-3574-47d9-b6e1-3d06ec1ea380' />
            <ref document='source-document00581.txt' feature='26d6e8cd-e007-467c-ad0f-d15de7e6c231' />
            <detail>
                <detail name='type'>copy_and_paste</detail>
            </detail>
        </match>
    </alignments>
</collusion>