<collusion score='0.0' system='sciplag'>
    <document id='suspicious-document01261.txt' src='suspicious-document01261.txt' original='suspicious-document01261.txt' format='txt'>
        <feature id='d4be25a0-cf2c-49b9-8222-fb087c1ad68e' type='translation' start='17416' length='574' value='null'/>
    </document>
    <document id='source-document01700.txt' src='source-document01700.txt' original='source-document01700.txt' format='txt'>
        <feature id='5dfab21d-b8a4-40a3-a732-f1622d24aac2' type='paragraph' start='1759' length='646' value='null'/>
    </document>
    <alignments>
        <match score='0.0' type='translation'>
            <ref document='suspicious-document01261.txt' feature='d4be25a0-cf2c-49b9-8222-fb087c1ad68e' />
            <ref document='source-document01700.txt' feature='5dfab21d-b8a4-40a3-a732-f1622d24aac2' />
            <detail>
                <detail name='type'>translation</detail>
            </detail>
        </match>
    </alignments>
</collusion>