<collusion score='0.0' system='sciplag'>
    <document id='suspicious-document01729.txt' src='suspicious-document01729.txt' original='suspicious-document01729.txt' format='txt'>
        <feature id='9155c837-fc53-4152-b517-e05a64f92ab7' type='shake_and_paste' start='868' length='209' value='null'/>
    </document>
    <document id='source-document00103.txt' src='source-document00103.txt' original='source-document00103.txt' format='txt'>
        <feature id='3fd153af-1753-49b6-8ab8-5914cdf13a27' type='paragraph' start='13848' length='322' value='null'/>
    </document>
    <alignments>
        <match score='0.0' type='shake_and_paste'>
            <ref document='suspicious-document01729.txt' feature='9155c837-fc53-4152-b517-e05a64f92ab7' />
            <ref document='source-document00103.txt' feature='3fd153af-1753-49b6-8ab8-5914cdf13a27' />
            <detail>
                <detail name='type'>shake_and_paste</detail>
            </detail>
        </match>
    </alignments>
</collusion>