<collusion score='0.0' system='sciplag'>
    <document id='suspicious-document01389.txt' src='suspicious-document01389.txt' original='suspicious-document01389.txt' format='txt'>
        <feature id='cc4d7b9b-190a-47b6-91a6-57cdcc6a48a1' type='copy_and_paste' start='26123' length='336' value='null'/>
    </document>
    <document id='source-document02062.txt' src='source-document02062.txt' original='source-document02062.txt' format='txt'>
        <feature id='7de1353b-6443-4425-bd3d-34508d1afcc8' type='paragraph' start='206' length='336' value='null'/>
    </document>
    <alignments>
        <match score='0.0' type='copy_and_paste'>
            <ref document='suspicious-document01389.txt' feature='cc4d7b9b-190a-47b6-91a6-57cdcc6a48a1' />
            <ref document='source-document02062.txt' feature='7de1353b-6443-4425-bd3d-34508d1afcc8' />
            <detail>
                <detail name='type'>copy_and_paste</detail>
            </detail>
        </match>
    </alignments>
</collusion>