<collusion score='0.0' system='sciplag'>
    <document id='suspicious-document01088.txt' src='suspicious-document01088.txt' original='suspicious-document01088.txt' format='txt'>
        <feature id='2d81136d-0e72-452e-b789-c62977c2ec11' type='summary' start='4319' length='637' value='null'/>
    </document>
    <document id='source-document02183.txt' src='source-document02183.txt' original='source-document02183.txt' format='txt'>
        <feature id='b9f4be7d-aee6-4933-83e4-09264fd34d04' type='paragraph' start='1' length='2472' value='null'/>
    </document>
    <alignments>
        <match score='0.0' type='summary'>
            <ref document='suspicious-document01088.txt' feature='2d81136d-0e72-452e-b789-c62977c2ec11' />
            <ref document='source-document02183.txt' feature='b9f4be7d-aee6-4933-83e4-09264fd34d04' />
            <detail>
                <detail name='type'>summary</detail>
            </detail>
        </match>
    </alignments>
</collusion>