<collusion score='0.0' system='sciplag'>
    <document id='suspicious-document00929.txt' src='suspicious-document00929.txt' original='suspicious-document00929.txt' format='txt'>
        <feature id='85ba6fa3-7ccd-4125-b23a-c2f188ac3c80' type='copy_and_paste' start='5191' length='862' value='null'/>
    </document>
    <document id='source-document02916.txt' src='source-document02916.txt' original='source-document02916.txt' format='txt'>
        <feature id='b894fb9b-1580-408b-ae96-1a78ff9c8105' type='paragraph' start='2356' length='862' value='null'/>
    </document>
    <alignments>
        <match score='0.0' type='copy_and_paste'>
            <ref document='suspicious-document00929.txt' feature='85ba6fa3-7ccd-4125-b23a-c2f188ac3c80' />
            <ref document='source-document02916.txt' feature='b894fb9b-1580-408b-ae96-1a78ff9c8105' />
            <detail>
                <detail name='type'>copy_and_paste</detail>
            </detail>
        </match>
    </alignments>
</collusion>