<collusion score='0.0' system='sciplag'>
    <document id='suspicious-document01778.txt' src='suspicious-document01778.txt' original='suspicious-document01778.txt' format='txt'>
        <feature id='3d36ee1b-844f-4bad-a824-5d1906eb69ee' type='shake_and_paste' start='13849' length='576' value='null'/>
        <feature id='f2c1c635-b3da-4b44-8886-0bece679cbaf' type='shake_and_paste' start='15178' length='489' value='null'/>
    </document>
    <document id='source-document03040.txt' src='source-document03040.txt' original='source-document03040.txt' format='txt'>
        <feature id='830cc488-a62a-405b-80df-7d8d62453ed6' type='paragraph' start='1547' length='672' value='null'/>
        <feature id='b2e14017-6e75-4b0f-9cc4-b0f103b4fb0f' type='paragraph' start='704' length='692' value='null'/>
    </document>
    <alignments>
        <match score='0.0' type='shake_and_paste'>
            <ref document='suspicious-document01778.txt' feature='3d36ee1b-844f-4bad-a824-5d1906eb69ee' />
            <ref document='source-document03040.txt' feature='830cc488-a62a-405b-80df-7d8d62453ed6' />
            <detail>
                <detail name='type'>shake_and_paste</detail>
            </detail>
        </match>
        <match score='0.0' type='shake_and_paste'>
            <ref document='suspicious-document01778.txt' feature='f2c1c635-b3da-4b44-8886-0bece679cbaf' />
            <ref document='source-document03040.txt' feature='b2e14017-6e75-4b0f-9cc4-b0f103b4fb0f' />
            <detail>
                <detail name='type'>shake_and_paste</detail>
            </detail>
        </match>
    </alignments>
</collusion>