<collusion score='0.0' system='sciplag'>
    <document id='suspicious-document00044.txt' src='suspicious-document00044.txt' original='suspicious-document00044.txt' format='txt'>
        <feature id='4f1ee00f-a2d0-4404-9de1-2cab32eddd17' type='copy_and_paste' start='3976' length='443' value='null'/>
        <feature id='e89c9c54-938e-47e1-abda-185e1206608d' type='copy_and_paste' start='8241' length='319' value='null'/>
        <feature id='a24eab58-d4df-45fa-83d6-da0572407913' type='copy_and_paste' start='9029' length='405' value='null'/>
    </document>
    <document id='source-document01326.txt' src='source-document01326.txt' original='source-document01326.txt' format='txt'>
        <feature id='826c3fb4-e35a-4382-9992-3bff69c61541' type='paragraph' start='299' length='443' value='null'/>
        <feature id='8c76281f-2df0-47b8-b957-e327ff96c8ee' type='paragraph' start='1714' length='319' value='null'/>
        <feature id='802fad16-9ec4-4963-8c24-17329447468d' type='paragraph' start='1144' length='405' value='null'/>
    </document>
    <alignments>
        <match score='0.0' type='copy_and_paste'>
            <ref document='suspicious-document00044.txt' feature='4f1ee00f-a2d0-4404-9de1-2cab32eddd17' />
            <ref document='source-document01326.txt' feature='826c3fb4-e35a-4382-9992-3bff69c61541' />
            <detail>
                <detail name='type'>copy_and_paste</detail>
            </detail>
        </match>
        <match score='0.0' type='copy_and_paste'>
            <ref document='suspicious-document00044.txt' feature='e89c9c54-938e-47e1-abda-185e1206608d' />
            <ref document='source-document01326.txt' feature='8c76281f-2df0-47b8-b957-e327ff96c8ee' />
            <detail>
                <detail name='type'>copy_and_paste</detail>
            </detail>
        </match>
        <match score='0.0' type='copy_and_paste'>
            <ref document='suspicious-document00044.txt' feature='a24eab58-d4df-45fa-83d6-da0572407913' />
            <ref document='source-document01326.txt' feature='802fad16-9ec4-4963-8c24-17329447468d' />
            <detail>
                <detail name='type'>copy_and_paste</detail>
            </detail>
        </match>
    </alignments>
</collusion>