<collusion score='0.0' system='sciplag'>
    <document id='suspicious-document01395.txt' src='suspicious-document01395.txt' original='suspicious-document01395.txt' format='txt'>
        <feature id='76af9eab-2b6c-4537-ae37-57197ed678e7' type='translation' start='7532' length='399' value='null'/>
    </document>
    <document id='source-document00478.txt' src='source-document00478.txt' original='source-document00478.txt' format='txt'>
        <feature id='a5e0e7e8-ade6-4be0-a8aa-ed04079058bd' type='paragraph' start='839' length='444' value='null'/>
    </document>
    <alignments>
        <match score='0.0' type='translation'>
            <ref document='suspicious-document01395.txt' feature='76af9eab-2b6c-4537-ae37-57197ed678e7' />
            <ref document='source-document00478.txt' feature='a5e0e7e8-ade6-4be0-a8aa-ed04079058bd' />
            <detail>
                <detail name='type'>translation</detail>
            </detail>
        </match>
    </alignments>
</collusion>