<collusion score='0.0' system='sciplag'>
    <document id='suspicious-document01271.txt' src='suspicious-document01271.txt' original='suspicious-document01271.txt' format='txt'>
        <feature id='9cc954d4-3181-400d-889b-c7d8c990c2df' type='translation' start='9592' length='360' value='null'/>
    </document>
    <document id='source-document02387.txt' src='source-document02387.txt' original='source-document02387.txt' format='txt'>
        <feature id='8b39e60b-de33-40ac-a85e-cb4773c1b100' type='paragraph' start='896' length='356' value='null'/>
    </document>
    <alignments>
        <match score='0.0' type='translation'>
            <ref document='suspicious-document01271.txt' feature='9cc954d4-3181-400d-889b-c7d8c990c2df' />
            <ref document='source-document02387.txt' feature='8b39e60b-de33-40ac-a85e-cb4773c1b100' />
            <detail>
                <detail name='type'>translation</detail>
            </detail>
        </match>
    </alignments>
</collusion>