<collusion score='0.0' system='sciplag'>
    <document id='suspicious-document00111.txt' src='suspicious-document00111.txt' original='suspicious-document00111.txt' format='txt'>
        <feature id='afaeaf26-2efd-401f-a047-4da4a11e6a0d' type='copy_and_paste' start='2072' length='735' value='null'/>
        <feature id='fbe3fe9f-437d-441b-8c04-ebd5485bfa43' type='copy_and_paste' start='29749' length='554' value='null'/>
    </document>
    <document id='source-document02107.txt' src='source-document02107.txt' original='source-document02107.txt' format='txt'>
        <feature id='2adc50cb-d3ce-4d4a-8178-f453416a34aa' type='paragraph' start='405' length='735' value='null'/>
        <feature id='a8daed48-10d5-43c0-853c-e27cf7c27173' type='paragraph' start='2014' length='554' value='null'/>
    </document>
    <alignments>
        <match score='0.0' type='copy_and_paste'>
            <ref document='suspicious-document00111.txt' feature='afaeaf26-2efd-401f-a047-4da4a11e6a0d' />
            <ref document='source-document02107.txt' feature='2adc50cb-d3ce-4d4a-8178-f453416a34aa' />
            <detail>
                <detail name='type'>copy_and_paste</detail>
            </detail>
        </match>
        <match score='0.0' type='copy_and_paste'>
            <ref document='suspicious-document00111.txt' feature='fbe3fe9f-437d-441b-8c04-ebd5485bfa43' />
            <ref document='source-document02107.txt' feature='a8daed48-10d5-43c0-853c-e27cf7c27173' />
            <detail>
                <detail name='type'>copy_and_paste</detail>
            </detail>
        </match>
    </alignments>
</collusion>