<collusion score='0.0' system='sciplag'>
    <document id='suspicious-document00011.txt' src='suspicious-document00011.txt' original='suspicious-document00011.txt' format='txt'>
        <feature id='d41b1653-7173-4153-a981-660d546fe703' type='translation' start='4220' length='760' value='null'/>
    </document>
    <document id='source-document01770.txt' src='source-document01770.txt' original='source-document01770.txt' format='txt'>
        <feature id='945d9417-2cf8-43bf-b5f6-1e7963ae278e' type='paragraph' start='4775' length='876' value='null'/>
    </document>
    <alignments>
        <match score='0.0' type='translation'>
            <ref document='suspicious-document00011.txt' feature='d41b1653-7173-4153-a981-660d546fe703' />
            <ref document='source-document01770.txt' feature='945d9417-2cf8-43bf-b5f6-1e7963ae278e' />
            <detail>
                <detail name='type'>translation</detail>
            </detail>
        </match>
    </alignments>
</collusion>