<collusion score='0.0' system='sciplag'>
    <document id='suspicious-document01629.txt' src='suspicious-document01629.txt' original='suspicious-document01629.txt' format='txt'>
        <feature id='e60fbad1-d61d-4219-901a-8ef57a39e358' type='translation' start='16516' length='451' value='null'/>
    </document>
    <document id='source-document01219.txt' src='source-document01219.txt' original='source-document01219.txt' format='txt'>
        <feature id='ecbf0c26-acf9-4f5d-a44b-32cf5731522f' type='paragraph' start='1742' length='452' value='null'/>
    </document>
    <alignments>
        <match score='0.0' type='translation'>
            <ref document='suspicious-document01629.txt' feature='e60fbad1-d61d-4219-901a-8ef57a39e358' />
            <ref document='source-document01219.txt' feature='ecbf0c26-acf9-4f5d-a44b-32cf5731522f' />
            <detail>
                <detail name='type'>translation</detail>
            </detail>
        </match>
    </alignments>
</collusion>