<collusion score='0.0' system='sciplag'>
    <document id='suspicious-document01560.txt' src='suspicious-document01560.txt' original='suspicious-document01560.txt' format='txt'>
        <feature id='be52b2e8-214f-4c9c-8c87-5070a313ffc9' type='translation' start='15839' length='373' value='null'/>
    </document>
    <document id='source-document01436.txt' src='source-document01436.txt' original='source-document01436.txt' format='txt'>
        <feature id='57fde2c4-bdcd-4142-814c-8c876ec3cde8' type='paragraph' start='1' length='377' value='null'/>
    </document>
    <alignments>
        <match score='0.0' type='translation'>
            <ref document='suspicious-document01560.txt' feature='be52b2e8-214f-4c9c-8c87-5070a313ffc9' />
            <ref document='source-document01436.txt' feature='57fde2c4-bdcd-4142-814c-8c876ec3cde8' />
            <detail>
                <detail name='type'>translation</detail>
            </detail>
        </match>
    </alignments>
</collusion>