<collusion score='0.0' system='sciplag'>
    <document id='suspicious-document01806.txt' src='suspicious-document01806.txt' original='suspicious-document01806.txt' format='txt'>
        <feature id='71f0d4f2-1c0d-4020-bb5e-80b66024e304' type='summary' start='2345' length='502' value='null'/>
    </document>
    <document id='source-document02146.txt' src='source-document02146.txt' original='source-document02146.txt' format='txt'>
        <feature id='f1e2d4e1-6e4e-45dd-851b-d8fd725cf7c2' type='paragraph' start='1' length='2432' value='null'/>
    </document>
    <alignments>
        <match score='0.0' type='summary'>
            <ref document='suspicious-document01806.txt' feature='71f0d4f2-1c0d-4020-bb5e-80b66024e304' />
            <ref document='source-document02146.txt' feature='f1e2d4e1-6e4e-45dd-851b-d8fd725cf7c2' />
            <detail>
                <detail name='type'>summary</detail>
            </detail>
        </match>
    </alignments>
</collusion>