<collusion score='0.0' system='sciplag'>
    <document id='suspicious-document00689.txt' src='suspicious-document00689.txt' original='suspicious-document00689.txt' format='txt'>
        <feature id='fd3c4e3e-07cf-4993-8c6b-50f40c88e4d1' type='shake_and_paste' start='5438' length='213' value='null'/>
        <feature id='06f62b44-3b29-43f6-8854-f5317ac33cd2' type='shake_and_paste' start='10887' length='355' value='null'/>
    </document>
    <document id='source-document00310.txt' src='source-document00310.txt' original='source-document00310.txt' format='txt'>
        <feature id='7c75558a-7e75-4998-aca3-a679a669eac4' type='paragraph' start='1298' length='349' value='null'/>
        <feature id='c2a76e8d-9431-4729-a0d8-e3daca7f1adc' type='paragraph' start='2643' length='444' value='null'/>
    </document>
    <alignments>
        <match score='0.0' type='shake_and_paste'>
            <ref document='suspicious-document00689.txt' feature='fd3c4e3e-07cf-4993-8c6b-50f40c88e4d1' />
            <ref document='source-document00310.txt' feature='7c75558a-7e75-4998-aca3-a679a669eac4' />
            <detail>
                <detail name='type'>shake_and_paste</detail>
            </detail>
        </match>
        <match score='0.0' type='shake_and_paste'>
            <ref document='suspicious-document00689.txt' feature='06f62b44-3b29-43f6-8854-f5317ac33cd2' />
            <ref document='source-document00310.txt' feature='c2a76e8d-9431-4729-a0d8-e3daca7f1adc' />
            <detail>
                <detail name='type'>shake_and_paste</detail>
            </detail>
        </match>
    </alignments>
</collusion>