<collusion score='0.0' system='sciplag'>
    <document id='suspicious-document01179.txt' src='suspicious-document01179.txt' original='suspicious-document01179.txt' format='txt'>
        <feature id='aab7e68c-5c91-4401-991a-f0bd45f291b7' type='translation' start='22270' length='550' value='null'/>
    </document>
    <document id='source-document01141.txt' src='source-document01141.txt' original='source-document01141.txt' format='txt'>
        <feature id='eb7effcc-6a56-4fe2-bd18-d3ffdc67a9ab' type='paragraph' start='1898' length='528' value='null'/>
    </document>
    <alignments>
        <match score='0.0' type='translation'>
            <ref document='suspicious-document01179.txt' feature='aab7e68c-5c91-4401-991a-f0bd45f291b7' />
            <ref document='source-document01141.txt' feature='eb7effcc-6a56-4fe2-bd18-d3ffdc67a9ab' />
            <detail>
                <detail name='type'>translation</detail>
            </detail>
        </match>
    </alignments>
</collusion>