<collusion score='0.0' system='sciplag'>
    <document id='suspicious-document00713.txt' src='suspicious-document00713.txt' original='suspicious-document00713.txt' format='txt'>
        <feature id='3d4871af-e547-4f73-a1eb-a3fbb3764875' type='summary' start='10620' length='642' value='null'/>
    </document>
    <document id='source-document01175.txt' src='source-document01175.txt' original='source-document01175.txt' format='txt'>
        <feature id='e97eb509-07fe-4fbf-a709-d66a9f471712' type='paragraph' start='1' length='3312' value='null'/>
    </document>
    <alignments>
        <match score='0.0' type='summary'>
            <ref document='suspicious-document00713.txt' feature='3d4871af-e547-4f73-a1eb-a3fbb3764875' />
            <ref document='source-document01175.txt' feature='e97eb509-07fe-4fbf-a709-d66a9f471712' />
            <detail>
                <detail name='type'>summary</detail>
            </detail>
        </match>
    </alignments>
</collusion>